.gitignore
CHANGES.txt
CONTRIBUTORS.txt
COPYRIGHT.txt
LICENSE.txt
MANIFEST.in
README.rst
rtd.txt
setup.cfg
setup.py
tox.ini
docs/.gitignore
docs/Makefile
docs/api.rst
docs/conf.py
docs/glossary.rst
docs/index.rst
docs/.static/logo_hi.gif
docs/.static/repoze.css
pyramid_mako/__init__.py
pyramid_mako/tests.py
pyramid_mako.egg-info/PKG-INFO
pyramid_mako.egg-info/SOURCES.txt
pyramid_mako.egg-info/dependency_links.txt
pyramid_mako.egg-info/not-zip-safe
pyramid_mako.egg-info/requires.txt
pyramid_mako.egg-info/top_level.txt
pyramid_mako/fixtures/components.mak
pyramid_mako/fixtures/hello .world.mako
pyramid_mako/fixtures/hello_inherit_pkg.mak
pyramid_mako/fixtures/hellocompo.mak
pyramid_mako/fixtures/helloinherit.mak
pyramid_mako/fixtures/helloworld.mak
pyramid_mako/fixtures/helloworld.mako
pyramid_mako/fixtures/layout.mak
pyramid_mako/fixtures/nonminimal.foo
pyramid_mako/fixtures/nonminimal.mak