Metadata-Version: 1.0
Name: pyramid-mako
Version: 0.3.1
Summary: Mako template bindings for the Pyramid web framework
Home-page: https://github.com/Pylons/pyramid_mako
Author: Bert JW Regeer
Author-email: pylons-discuss@googlegroups.com
License: BSD-derived (http://www.repoze.org/LICENSE.txt)
Keywords: web wsgi pylons pyramid
Platform: UNKNOWN
Classifier: Intended Audience :: Developers
Classifier: Programming Language :: Python
Classifier: Programming Language :: Python :: 2.5
Classifier: Programming Language :: Python :: 2.6
Classifier: Programming Language :: Python :: 2.7
Classifier: Programming Language :: Python :: 3
Classifier: Programming Language :: Python :: 3.2
Classifier: Programming Language :: Python :: 3.3
Classifier: Framework :: Pylons
Classifier: License :: Repoze Public License
